dbnd_examples/__init__.py
dbnd_examples/conftest.py
dbnd_examples/data.py
dbnd_examples/dbnd_airflow/__init__.py
dbnd_examples/dbnd_airflow/bash_dag.py
dbnd_examples/dbnd_airflow/python_op_dag.py
dbnd_examples/dbnd_airflow/snowflake/__init__.py
dbnd_examples/dbnd_airflow/snowflake/snowflake_dag.py
dbnd_examples/dbnd_airflow/snowflake/snowflake_log_hook_dag.py
dbnd_examples/dbnd_spark/__init__.py
dbnd_examples/dbnd_spark/spark_jvm/pom.xml
dbnd_examples/dbnd_spark/spark_jvm/src/main/java/ai/databand/examples/AddDressing.java
dbnd_examples/dbnd_spark/spark_jvm/src/main/java/ai/databand/examples/Cut.java
dbnd_examples/dbnd_spark/spark_jvm/src/main/java/ai/databand/examples/WordCount.java
dbnd_examples/dbnd_spark/spark_jvm/src/main/java/ai/databand/examples/WordCountWithHtml.java
dbnd_examples/tests/__init__.py
dbnd_examples/tests/documentation/__init__.py
dbnd_examples/tests/documentation/tracking/__init__.py
dbnd_examples/tests/documentation/tracking/test_doc_airflow_and_snowflake.py
dbnd_examples/tests/documentation/tracking/test_doc_explicit_dataset_logging.py
dbnd_examples/tests/documentation/tracking/test_doc_functions.py
dbnd_examples/tests/documentation/tracking/test_doc_metrics.py
dbnd_examples/tests/documentation/tracking/test_doc_performant_logging.py
dbnd_examples/tests/documentation/tracking/test_doc_pyspark_dataframe.py
dbnd_examples/tests/documentation/tracking/test_doc_python_scripts.py
dbnd_examples/tests/documentation/tracking/test_doc_tracking_airflow_dags.py
dbnd_examples/tests/documentation/tracking/test_doc_tracking_databricks.py
dbnd_examples/tests/documentation/tracking/test_doc_tracking_mlflow.py
dbnd_examples/tests/documentation/tracking/test_doc_tracking_pandas_dataframe.py
dbnd_examples/tests/documentation/tracking/test_doc_tracking_quickstart.py
dbnd_examples/tests/documentation/tracking/test_doc_tracking_redshift.py
dbnd_examples/tests/documentation/tracking/test_doc_tracking_snowflake_guide.py
dbnd_examples-1.0.30.1.dist-info/LICENSE
dbnd_examples-1.0.30.1.dist-info/METADATA
dbnd_examples-1.0.30.1.dist-info/WHEEL
dbnd_examples-1.0.30.1.dist-info/top_level.txt
dbnd_examples-1.0.30.1.dist-info/RECORD
